alu.v
module alu (
    input  [3:0] a,
    input  [3:0] b,
    input  [2:0] op,
    output reg [4:0] result,
    output reg overflow
);

always @(*) begin
    overflow = 0;

    if (op == 3'b000) begin
        result   = a + b;
        if (a[3] == 0 && b[3] == 0 && result[3] == 1)
            overflow = 1;
    end

    else if (op == 3'b001) begin
        result   = a - b;
        if (a[3] == 0 && b[3] == 1 && result[3] == 1)
            overflow = 1;
    end

    else if (op == 3'b010)
        result = a & b;

    else if (op == 3'b011)
        result = a | b;

    else if (op == 3'b100)
        result = a ^ b;

    else if (op == 3'b101)
        result = ~a;

    else if (op == 3'b110)
        result = a << 1;

    else if (op == 3'b111)
        result = a >> 1;

    else
        result = 0;
end

endmodule

alu_tb.v
module alu_tb;

// declare inputs as reg (we drive them)
reg [3:0] a;
reg [3:0] b;
reg [2:0] op;

// declare outputs as wire (ALU drives them)
wire [4:0] result;
wire       overflow;

// count pass and fail
integer pass;
integer fail;

// connect testbench to ALU
alu uut (
    .a(a),
    .b(b),
    .op(op),
    .result(result),
    .overflow(overflow)
);

initial begin

    // open waveform file for GTKWave
    $dumpfile("alu.vcd");
    $dumpvars(0, alu_tb);

    pass = 0;
    fail = 0;

    // ==============================
    // TEST 1 — ADD normal
    // ==============================
    a = 4'd3; b = 4'd4; op = 3'b000;
    #10;
    if (result == 5'd7 && overflow == 0) begin
        $display("PASS | ADD normal  | a=3  b=4  | result=%0d overflow=%0b", result, overflow);
        pass = pass + 1;
    end else begin
        $display("FAIL | ADD normal  | a=3  b=4  | expected=7  ov=0 | got=%0d ov=%0b", result, overflow);
        fail = fail + 1;
    end

    // ==============================
    // TEST 2 — ADD overflow
    // 7+1 = 8 which overflows signed 4-bit
    // ==============================
    a = 4'd7; b = 4'd1; op = 3'b000;
    #10;
    if (result == 5'd8 && overflow == 1) begin
        $display("PASS | ADD overflow | a=7  b=1  | result=%0d overflow=%0b", result, overflow);
        pass = pass + 1;
    end else begin
        $display("FAIL | ADD overflow | a=7  b=1  | expected=8  ov=1 | got=%0d ov=%0b", result, overflow);
        fail = fail + 1;
    end

    // ==============================
    // TEST 3 — SUB normal
    // ==============================
    a = 4'd9; b = 4'd5; op = 3'b001;
    #10;
    if (result == 5'd4 && overflow == 0) begin
        $display("PASS | SUB normal  | a=9  b=5  | result=%0d overflow=%0b", result, overflow);
        pass = pass + 1;
    end else begin
        $display("FAIL | SUB normal  | a=9  b=5  | expected=4  ov=0 | got=%0d ov=%0b", result, overflow);
        fail = fail + 1;
    end

    // ==============================
    // TEST 4 — AND
    // 1100 & 1010 = 1000
    // ==============================
    a = 4'b1100; b = 4'b1010; op = 3'b010;
    #10;
    if (result == 5'b01000 && overflow == 0) begin
        $display("PASS | AND         | a=12 b=10 | result=%0d overflow=%0b", result, overflow);
        pass = pass + 1;
    end else begin
        $display("FAIL | AND         | a=12 b=10 | expected=8  ov=0 | got=%0d ov=%0b", result, overflow);
        fail = fail + 1;
    end

    // ==============================
    // TEST 5 — OR
    // 1100 | 1010 = 1110
    // ==============================
    a = 4'b1100; b = 4'b1010; op = 3'b011;
    #10;
    if (result == 5'b01110 && overflow == 0) begin
        $display("PASS | OR          | a=12 b=10 | result=%0d overflow=%0b", result, overflow);
        pass = pass + 1;
    end else begin
        $display("FAIL | OR          | a=12 b=10 | expected=14 ov=0 | got=%0d ov=%0b", result, overflow);
        fail = fail + 1;
    end

    // ==============================
    // TEST 6 — XOR
    // 1100 ^ 1010 = 0110
    // ==============================
    a = 4'b1100; b = 4'b1010; op = 3'b100;
    #10;
    if (result == 5'b00110 && overflow == 0) begin
        $display("PASS | XOR         | a=12 b=10 | result=%0d overflow=%0b", result, overflow);
        pass = pass + 1;
    end else begin
        $display("FAIL | XOR         | a=12 b=10 | expected=6  ov=0 | got=%0d ov=%0b", result, overflow);
        fail = fail + 1;
    end

    // ==============================
    // TEST 7 — NOT
    // ~1010 = 0101
    // ==============================
    a = 4'b1010; b = 4'd0; op = 3'b101;
    #10;
    if (result == 5'b00101 && overflow == 0) begin
        $display("PASS | NOT         | a=10      | result=%0d overflow=%0b", result, overflow);
        pass = pass + 1;
    end else begin
        $display("FAIL | NOT         | a=10      | expected=5  ov=0 | got=%0d ov=%0b", result, overflow);
        fail = fail + 1;
    end

    // ==============================
    // TEST 8 — SHIFT LEFT
    // 0011 << 1 = 0110
    // ==============================
    a = 4'b0011; b = 4'd0; op = 3'b110;
    #10;
    if (result == 5'b00110 && overflow == 0) begin
        $display("PASS | SHL         | a=3       | result=%0d overflow=%0b", result, overflow);
        pass = pass + 1;
    end else begin
        $display("FAIL | SHL         | a=3       | expected=6  ov=0 | got=%0d ov=%0b", result, overflow);
        fail = fail + 1;
    end

    // ==============================
    // TEST 9 — SHIFT RIGHT
    // 1100 >> 1 = 0110
    // ==============================
    a = 4'b1100; b = 4'd0; op = 3'b111;
    #10;
    if (result == 5'b00110 && overflow == 0) begin
        $display("PASS | SHR         | a=12      | result=%0d overflow=%0b", result, overflow);
        pass = pass + 1;
    end else begin
        $display("FAIL | SHR         | a=12      | expected=6  ov=0 | got=%0d ov=%0b", result, overflow);
        fail = fail + 1;
    end

    // ==============================
    // FINAL SUMMARY
    // ==============================
    $display("--------------------------------");
    $display("RESULT: %0d PASS  |  %0d FAIL", pass, fail);
    $display("--------------------------------");

    $finish;
end

endmodule

alu.vcd
$date
	Sat Apr 18 13:42:20 2026
$end
$version
	Icarus Verilog
$end
$timescale
	1s
$end
$scope module alu_tb $end
$var wire 5 ! result [4:0] $end
$var wire 1 " overflow $end
$var reg 4 # a [3:0] $end
$var reg 4 $ b [3:0] $end
$var reg 3 % op [2:0] $end
$var integer 32 & fail [31:0] $end
$var integer 32 ' pass [31:0] $end
$scope module uut $end
$var wire 4 ( a [3:0] $end
$var wire 4 ) b [3:0] $end
$var wire 3 * op [2:0] $end
$var reg 1 " overflow $end
$var reg 5 + result [4:0] $end
$upscope $end
$upscope $end
$enddefinitions $end
$comment Show the parameter values. $end
$dumpall
$end
#0
$dumpvars
b111 +
b0 *
b100 )
b11 (
b0 '
b0 &
b0 %
b100 $
b11 #
0"
b111 !
$end
#10
1"
b1000 !
b1000 +
b1 $
b1 )
b111 #
b111 (
b1 '
#20
b100 !
b100 +
0"
b1 %
b1 *
b101 $
b101 )
b1001 #
b1001 (
b10 '
#30
b1000 !
b1000 +
b10 %
b10 *
b1010 $
b1010 )
b1100 #
b1100 (
b11 '
#40
b1110 !
b1110 +
b11 %
b11 *
b100 '
#50
b110 !
b110 +
b100 %
b100 *
b101 '
#60
b10101 !
b10101 +
b101 %
b101 *
b0 $
b0 )
b1010 #
b1010 (
b110 '
#70
b110 !
b110 +
b110 %
b110 *
b11 #
b11 (
b1 &
#80
b111 %
b111 *
b1100 #
b1100 (
b111 '
#90
b1000 '
